<?xml version="1.0" encoding="utf-8"?>
<LanguageData>

    <!--水晶-->
    <TNA_crystal.label>水晶</TNA_crystal.label>
    <TNA_crystal.description>这或许是世界上最神秘最强大的物质。尽管它的元素组成已经被解析，但还是不清楚它与EVE粒子的作用机理。\n这种晶体的培养方式只被少数组织垄断着，然而它丰富的特性却已经使它成为工业生产中不可缺少的材料。</TNA_crystal.description>
    
    <!--水晶纤维-->
    <TNA_crystalfiber.label>水晶纤维</TNA_crystalfiber.label>
    <TNA_crystalfiber.description>由水晶和高分子材料经过特殊工艺加工而成的纤维，物理性质是所有织物中最优秀的。\n这种纤维的制造工艺只有Elements掌握，他们的所有成员都身着这种材料制成的衣物，这也区别他们身份的一种方法。</TNA_crystalfiber.description>
</LanguageData>